enzeptional/__init__.py
enzeptional/core.py
enzeptional/processing.py
enzeptional/resources/__init__.py
enzeptional/resources/kcat_sample_model/model.pkl
enzeptional/resources/kcat_sample_model/scaler.pkl
enzeptional-1.0.4.dist-info/LICENSE
enzeptional-1.0.4.dist-info/METADATA
enzeptional-1.0.4.dist-info/WHEEL
enzeptional-1.0.4.dist-info/top_level.txt
enzeptional-1.0.4.dist-info/RECORD
