Metadata-Version: 2.1
Name: enzeptional
Version: 1.0.4
Summary: Enzeptional stand-alone python package.
Author: GT4SD team
Classifier: Operating System :: OS Independent
Classifier: Programming Language :: Python :: 3
Classifier: Programming Language :: Python :: 3.8
Classifier: Programming Language :: Python :: 3.9
Classifier: Programming Language :: Python :: 3.10
License-File: LICENSE
Requires-Dist: transformers <5.0.0,>=4.22.0
Requires-Dist: torch <=1.12.1,>=1.0
Requires-Dist: numpy <2.0.0,>=1.16.5
Requires-Dist: pandas <=2.0.3
Requires-Dist: joblib >=1.1.0
Requires-Dist: xgboost >=1.7.6
Requires-Dist: importlib-resources >=5.10.0
Requires-Dist: tape-proteins >=0.4
Requires-Dist: scikit-learn <1.3.0,>=1.0.0
Provides-Extra: dev
Requires-Dist: black ; extra == 'dev'
Requires-Dist: isort ; extra == 'dev'
Requires-Dist: mypy ; extra == 'dev'
Requires-Dist: flake8 ; extra == 'dev'
Requires-Dist: pytest ; extra == 'dev'
